{"133":{"fip":4.09,"xwoba":null,"whip":1.45,"woba":0.34},"134":{"fip":4.04,"xwoba":null,"whip":1.33,"woba":0.311},"135":{"fip":3.53,"xwoba":null,"whip":1.21,"woba":0.294},"136":{"fip":3.75,"xwoba":null,"whip":1.32,"woba":0.303},"137":{"fip":3.78,"xwoba":null,"whip":1.26,"woba":0.283},"138":{"fip":4.27,"xwoba":null,"whip":1.3,"woba":0.307},"139":{"fip":4.05,"xwoba":null,"whip":1.22,"woba":0.308},"140":{"fip":3.89,"xwoba":null,"whip":1.21,"woba":0.291},"141":{"fip":3.08,"xwoba":null,"whip":1.21,"woba":0.278},"142":{"fip":4.13,"xwoba":null,"whip":1.39,"woba":0.312},"143":{"fip":3.45,"xwoba":null,"whip":1.24,"woba":0.303},"144":{"fip":3.12,"xwoba":null,"whip":1.04,"woba":0.264},"145":{"fip":3.88,"xwoba":null,"whip":1.28,"woba":0.3},"146":{"fip":3.93,"xwoba":null,"whip":1.29,"woba":0.303},"147":{"fip":3.7,"xwoba":null,"whip":1.19,"woba":0.288},"158":{"fip":3.4,"xwoba":null,"whip":1.17,"woba":0.284},"108":{"fip":3.94,"xwoba":null,"whip":1.29,"woba":0.307},"109":{"fip":3.63,"xwoba":null,"whip":1.09,"woba":0.279},"110":{"fip":3.66,"xwoba":null,"whip":1.16,"woba":0.291},"111":{"fip":3.61,"xwoba":null,"whip":1.16,"woba":0.288},"112":{"fip":5.07,"xwoba":null,"whip":1.35,"woba":0.328},"113":{"fip":4.51,"xwoba":null,"whip":1.24,"woba":0.301},"114":{"fip":3.34,"xwoba":null,"whip":1.23,"woba":0.291},"115":{"fip":4.36,"xwoba":null,"whip":1.5,"woba":0.344},"116":{"fip":4.46,"xwoba":null,"whip":1.32,"woba":0.323},"117":{"fip":4.21,"xwoba":null,"whip":1.24,"woba":0.302},"118":{"fip":5.02,"xwoba":null,"whip":1.41,"woba":0.337},"119":{"fip":3.13,"xwoba":null,"whip":1.05,"woba":0.255},"120":{"fip":4.59,"xwoba":null,"whip":1.5,"woba":0.333},"121":{"fip":3.67,"xwoba":null,"whip":1.23,"woba":0.297}}